rs1090-0.5.1.dist-info/METADATA
rs1090-0.5.1.dist-info/WHEEL
rs1090.libs/libgcc_s-f685abf1.so.1
rs1090/__init__.py
rs1090/_rust.pyi
rs1090/_rust.pypy311-pp73-x86_64-linux-gnu.so
rs1090/py.typed
rs1090/stubs.py
rs1090-0.5.1.dist-info/RECORD
