Metadata-Version: 2.4
Name: rs1090
Version: 0.5.1
Classifier: Programming Language :: Rust
Classifier: Programming Language :: Python :: Implementation :: CPython
Classifier: Programming Language :: Python :: Implementation :: PyPy
Requires-Dist: pandas>=2.2.0
Requires-Dist: typing-extensions>=4.10.0
License-Expression: MIT
Requires-Python: >=3.10
Project-URL: repository, https://github.com/xoolive/jet1090
